[{"recipient":"ghh musq@ss.bbb","time":"23-Feb-2016 13:11","subject":"Pending Visit to Rufai Jalal","id":"musq@ss.bbb23rd Feb 2016 13 111551.php","status":0},{"recipient":"Rufai Jalal pat3echo@gmail.com","time":"23-Feb-2016 13:11","subject":"Pending Visit from ghh","id":"pat3echo@gmail.com23rd Feb 2016 13 118999.php","status":0},{"recipient":"ghh musq@ss.bbb","time":"23-Feb-2016 13:16","subject":"Pending Visit to Rufai Jalal","id":"musq@ss.bbb23rd Feb 2016 13 165552.php","status":0},{"recipient":"Rufai Jalal pat3echo@gmail.com","time":"23-Feb-2016 13:16","subject":"Pending Visit from ghh","id":"pat3echo@gmail.com23rd Feb 2016 13 162536.php","status":0},{"recipient":"Test 1 test@gmail.com","time":"23-Feb-2016 13:22","subject":"Approved Visit for 23-Feb-2016","id":"test@gmail.com23rd Feb 2016 13 22241.php","status":0},{"recipient":"Test 1 test@gmail.com","time":"23-Feb-2016 13:23","subject":"Declined Visit for 19-Feb-2016","id":"test@gmail.com23rd Feb 2016 13 231362.php","status":0},{"recipient":"Test 1 test@gmail.com","time":"23-Feb-2016 13:23","subject":"Approved Visit for 23-Feb-2016","id":"test@gmail.com23rd Feb 2016 13 236109.php","status":0}]