{"11873681428W1":{"id":"11873681428W1","serial_num":"302","creation_date":"1475735115","modification_date":"1475735115","transaction_id":"11873681427","account":"accounts_receivable","amount":"5128.00","type":"credit","account_type":"accounts_receivable","extra_reference":"11873681425","currency":"","comment":""},"11873681428W2":{"id":"11873681428W2","serial_num":"303","creation_date":"1475735115","modification_date":"1475735115","transaction_id":"11873681427","account":"cash_book","amount":"5128.00","type":"debit","account_type":"cash_book","extra_reference":"11873681425","currency":"","comment":""}}