{"11470566528W1":{"id":"11470566528W1","serial_num":"1384","creation_date":"1471700366","modification_date":"1471700366","transaction_id":"11470566527","account":"11097149545","amount":"1900.00","type":"debit","account_type":"account_payable","extra_reference":"","currency":""},"11470566528W2":{"id":"11470566528W2","serial_num":"1385","creation_date":"1471700366","modification_date":"1471700366","transaction_id":"11470566527","account":"cash_payment","amount":"1900.00","type":"credit","account_type":"cash_payment","extra_reference":"","currency":""}}