{"112012538681":{"id":"112012538681","serial_num":"39","creation_date":"1469007239","modification_date":"1469007239","transaction_id":"11201253747","account":"inventory","amount":"2364","type":"debit","account_type":"inventory"},"112012538682":{"id":"112012538682","serial_num":"40","creation_date":"1469007239","modification_date":"1469007239","transaction_id":"11201253747","account":"10986160518","amount":"2364","type":"credit","account_type":"account_payable"},"112012538683":{"id":"112012538683","serial_num":"41","creation_date":"1469007239","modification_date":"1469007239","transaction_id":"11201253747","account":"10986160518","amount":"2364","type":"debit","account_type":"account_payable"},"112012538684":{"id":"112012538684","serial_num":"42","creation_date":"1469007239","modification_date":"1469007239","transaction_id":"11201253747","account":"bank1","amount":"2364","type":"credit","account_type":"bank1"}}