{"11874628559W1":{"id":"11874628559W1","serial_num":"398","creation_date":"1475744586","modification_date":"1475744586","transaction_id":"11874628558","account":"11651372719","amount":"10000.00","type":"credit","account_type":"accounts_receivable","extra_reference":"11874543414","currency":"","comment":"#S00032 - 06-Oct-2016"},"11874628559W3":{"id":"11874628559W3","serial_num":"400","creation_date":"1475744586","modification_date":"1475744586","transaction_id":"11874628558","account":"11695660154","amount":"8000.00","type":"credit","account_type":"accounts_receivable","extra_reference":"11874529175","currency":"","comment":"#S00031 - 06-Oct-2016"},"11874628559W2":{"id":"11874628559W2","serial_num":"399","creation_date":"1475744586","modification_date":"1475744586","transaction_id":"11874628558","account":"bank1","amount":"18000.00","type":"debit","account_type":"cash_book","extra_reference":"","currency":"","comment":""}}