{"1467007155":{"id":"1467007155","price":"$1,040.00","text":"2151","quantity":1,"image":"2151.png","weight":"13g"},"1467007156":{"id":"1467007156","price":"$1,040.00","text":"2152","quantity":1,"image":"2152.png","weight":"13g"},"1467007157":{"id":"1467007157","price":"$560.00","text":"2153","quantity":1,"image":"2153.png","weight":"7g"},"1467007158":{"id":"1467007158","price":"$2,656.00","text":"2154","quantity":1,"image":"2154.png","weight":"33.2g"},"1467007159":{"id":"1467007159","price":"$2,264.00","text":"2155","quantity":1,"image":"2155.png","weight":"28.3g"},"1467007160":{"id":"1467007160","price":"$856.00","text":"2156","quantity":1,"image":"2156.png","weight":"10.7g"},"1467007161":{"id":"1467007161","price":"$696.00","text":"2157","quantity":1,"image":"2157.png","weight":"8.7g"},"1467007162":{"id":"1467007162","price":"$1,576.00","text":"2158","quantity":1,"image":"2158.png","weight":"19.7g"},"1467007163":{"id":"1467007163","price":"$1,488.00","text":"2159","quantity":1,"image":"2159.png","weight":"18.6g"},"1467007164":{"id":"1467007164","price":"$1,808.00","text":"2160","quantity":1,"image":"2160.png","weight":"22.6g"},"1467007165":{"id":"1467007165","price":"$720.00","text":"2161","quantity":1,"image":"2161.png","weight":"9g"},"1467007166":{"id":"1467007166","price":"$1,144.00","text":"2162","quantity":1,"image":"2162.png","weight":"14.3g"}}