[{"user":"35991362173","user_mail":"Hyella Nathan ( hyella@gmail.com )","user_action":"UPDATE","table":"category","comment":"UPDATE `water_factory`.`category` SET `id` = 'senioratiku' , `category001` = 'Senior Atiku' , `category002` = 'purchased_goods' , `modified_by` = '35991362173' , `modification_date` = '1477570304' , `ip_address` = '::1' , `record_status` = '1' WHERE `id` = 'senioratiku'","date":"1477570307","ip_address":"::1"},{"user":"35991362173","user_mail":"Hyella Nathan ( hyella@gmail.com )","user_action":"EXECUTE","table":"access_roles","comment":"TRUNCATE `water_factory`.`access_roles`","date":"1477570650","ip_address":"::1"},{"user":"35991362173","user_mail":"Hyella Nathan ( hyella@gmail.com )","user_action":"EXECUTE","table":"access_roles","comment":"LOAD DATA INFILE 'C:\/hyella\/htdocs\/feyi\/engine\/tmp\/db\/00-FF-5C-09-DA-57\/access_roles.sql' INTO TABLE access_roles","date":"1477570650","ip_address":"::1"},{"user":"35991362173","user_mail":"Hyella Nathan ( hyella@gmail.com )","user_action":"EXECUTE","table":"assets","comment":"TRUNCATE `water_factory`.`assets`","date":"1477570650","ip_address":"::1"},{"user":"35991362173","user_mail":"Hyella Nathan ( hyella@gmail.com )","user_action":"EXECUTE","table":"assets","comment":"LOAD DATA INFILE 'C:\/hyella\/htdocs\/feyi\/engine\/tmp\/db\/00-FF-5C-09-DA-57\/assets.sql' INTO TABLE assets","date":"1477570651","ip_address":"::1"},{"user":"35991362173","user_mail":"Hyella Nathan ( hyella@gmail.com )","user_action":"EXECUTE","table":"assets_category","comment":"TRUNCATE `water_factory`.`assets_category`","date":"1477570651","ip_address":"::1"},{"user":"35991362173","user_mail":"Hyella Nathan ( hyella@gmail.com )","user_action":"EXECUTE","table":"assets_category","comment":"LOAD DATA INFILE 'C:\/hyella\/htdocs\/feyi\/engine\/tmp\/db\/00-FF-5C-09-DA-57\/assets_category.sql' INTO TABLE assets_category","date":"1477570651","ip_address":"::1"},{"user":"35991362173","user_mail":"Hyella Nathan ( hyella@gmail.com )","user_action":"EXECUTE","table":"branch_offices","comment":"TRUNCATE `water_factory`.`branch_offices`","date":"1477570651","ip_address":"::1"},{"user":"35991362173","user_mail":"Hyella Nathan ( hyella@gmail.com )","user_action":"EXECUTE","table":"branch_offices","comment":"LOAD DATA INFILE 'C:\/hyella\/htdocs\/feyi\/engine\/tmp\/db\/00-FF-5C-09-DA-57\/branch_offices.sql' INTO TABLE branch_offices","date":"1477570651","ip_address":"::1"},{"user":"35991362173","user_mail":"Hyella Nathan ( hyella@gmail.com )","user_action":"EXECUTE","table":"category","comment":"TRUNCATE `water_factory`.`category`","date":"1477570651","ip_address":"::1"},{"user":"35991362173","user_mail":"Hyella Nathan ( hyella@gmail.com )","user_action":"EXECUTE","table":"category","comment":"LOAD DATA INFILE 'C:\/hyella\/htdocs\/feyi\/engine\/tmp\/db\/00-FF-5C-09-DA-57\/category.sql' INTO TABLE category","date":"1477570652","ip_address":"::1"},{"user":"35991362173","user_mail":"Hyella Nathan ( hyella@gmail.com )","user_action":"EXECUTE","table":"chart_of_accounts","comment":"TRUNCATE `water_factory`.`chart_of_accounts`","date":"1477570652","ip_address":"::1"},{"user":"35991362173","user_mail":"Hyella Nathan ( hyella@gmail.com )","user_action":"EXECUTE","table":"chart_of_accounts","comment":"LOAD DATA INFILE 'C:\/hyella\/htdocs\/feyi\/engine\/tmp\/db\/00-FF-5C-09-DA-57\/chart_of_accounts.sql' INTO TABLE chart_of_accounts","date":"1477570652","ip_address":"::1"},{"user":"35991362173","user_mail":"Hyella Nathan ( hyella@gmail.com )","user_action":"EXECUTE","table":"cities_list","comment":"TRUNCATE `water_factory`.`cities_list`","date":"1477570652","ip_address":"::1"},{"user":"35991362173","user_mail":"Hyella Nathan ( hyella@gmail.com )","user_action":"EXECUTE","table":"cities_list","comment":"LOAD DATA INFILE 'C:\/hyella\/htdocs\/feyi\/engine\/tmp\/db\/00-FF-5C-09-DA-57\/cities_list.sql' INTO TABLE cities_list","date":"1477570653","ip_address":"::1"},{"user":"35991362173","user_mail":"Hyella Nathan ( hyella@gmail.com )","user_action":"EXECUTE","table":"country_list","comment":"TRUNCATE `water_factory`.`country_list`","date":"1477570653","ip_address":"::1"},{"user":"35991362173","user_mail":"Hyella Nathan ( hyella@gmail.com )","user_action":"EXECUTE","table":"country_list","comment":"LOAD DATA INFILE 'C:\/hyella\/htdocs\/feyi\/engine\/tmp\/db\/00-FF-5C-09-DA-57\/country_list.sql' INTO TABLE country_list","date":"1477570653","ip_address":"::1"},{"user":"35991362173","user_mail":"Hyella Nathan ( hyella@gmail.com )","user_action":"EXECUTE","table":"customers","comment":"TRUNCATE `water_factory`.`customers`","date":"1477570653","ip_address":"::1"},{"user":"35991362173","user_mail":"Hyella Nathan ( hyella@gmail.com )","user_action":"EXECUTE","table":"customers","comment":"LOAD DATA INFILE 'C:\/hyella\/htdocs\/feyi\/engine\/tmp\/db\/00-FF-5C-09-DA-57\/customers.sql' INTO TABLE customers","date":"1477570654","ip_address":"::1"},{"user":"35991362173","user_mail":"Hyella Nathan ( hyella@gmail.com )","user_action":"EXECUTE","table":"damages","comment":"TRUNCATE `water_factory`.`damages`","date":"1477570654","ip_address":"::1"},{"user":"35991362173","user_mail":"Hyella Nathan ( hyella@gmail.com )","user_action":"EXECUTE","table":"damages","comment":"LOAD DATA INFILE 'C:\/hyella\/htdocs\/feyi\/engine\/tmp\/db\/00-FF-5C-09-DA-57\/damages.sql' INTO TABLE damages","date":"1477570654","ip_address":"::1"},{"user":"35991362173","user_mail":"Hyella Nathan ( hyella@gmail.com )","user_action":"EXECUTE","table":"debit_and_credit","comment":"TRUNCATE `water_factory`.`debit_and_credit`","date":"1477570654","ip_address":"::1"},{"user":"35991362173","user_mail":"Hyella Nathan ( hyella@gmail.com )","user_action":"EXECUTE","table":"debit_and_credit","comment":"LOAD DATA INFILE 'C:\/hyella\/htdocs\/feyi\/engine\/tmp\/db\/00-FF-5C-09-DA-57\/debit_and_credit.sql' INTO TABLE debit_and_credit","date":"1477570654","ip_address":"::1"},{"user":"35991362173","user_mail":"Hyella Nathan ( hyella@gmail.com )","user_action":"EXECUTE","table":"debit_and_credit_draft","comment":"TRUNCATE `water_factory`.`debit_and_credit_draft`","date":"1477570654","ip_address":"::1"},{"user":"35991362173","user_mail":"Hyella Nathan ( hyella@gmail.com )","user_action":"EXECUTE","table":"debit_and_credit_draft","comment":"LOAD DATA INFILE 'C:\/hyella\/htdocs\/feyi\/engine\/tmp\/db\/00-FF-5C-09-DA-57\/debit_and_credit_draft.sql' INTO TABLE debit_and_credit_draft","date":"1477570655","ip_address":"::1"},{"user":"35991362173","user_mail":"Hyella Nathan ( hyella@gmail.com )","user_action":"EXECUTE","table":"departments","comment":"TRUNCATE `water_factory`.`departments`","date":"1477570655","ip_address":"::1"},{"user":"35991362173","user_mail":"Hyella Nathan ( hyella@gmail.com )","user_action":"EXECUTE","table":"departments","comment":"LOAD DATA INFILE 'C:\/hyella\/htdocs\/feyi\/engine\/tmp\/db\/00-FF-5C-09-DA-57\/departments.sql' INTO TABLE departments","date":"1477570655","ip_address":"::1"},{"user":"35991362173","user_mail":"Hyella Nathan ( hyella@gmail.com )","user_action":"EXECUTE","table":"discount","comment":"TRUNCATE `water_factory`.`discount`","date":"1477570655","ip_address":"::1"},{"user":"35991362173","user_mail":"Hyella Nathan ( hyella@gmail.com )","user_action":"EXECUTE","table":"discount","comment":"LOAD DATA INFILE 'C:\/hyella\/htdocs\/feyi\/engine\/tmp\/db\/00-FF-5C-09-DA-57\/discount.sql' INTO TABLE discount","date":"1477570656","ip_address":"::1"},{"user":"35991362173","user_mail":"Hyella Nathan ( hyella@gmail.com )","user_action":"EXECUTE","table":"division","comment":"TRUNCATE `water_factory`.`division`","date":"1477570656","ip_address":"::1"},{"user":"35991362173","user_mail":"Hyella Nathan ( hyella@gmail.com )","user_action":"EXECUTE","table":"division","comment":"LOAD DATA INFILE 'C:\/hyella\/htdocs\/feyi\/engine\/tmp\/db\/00-FF-5C-09-DA-57\/division.sql' INTO TABLE division","date":"1477570656","ip_address":"::1"},{"user":"35991362173","user_mail":"Hyella Nathan ( hyella@gmail.com )","user_action":"EXECUTE","table":"expenditure","comment":"TRUNCATE `water_factory`.`expenditure`","date":"1477570656","ip_address":"::1"},{"user":"35991362173","user_mail":"Hyella Nathan ( hyella@gmail.com )","user_action":"EXECUTE","table":"expenditure","comment":"LOAD DATA INFILE 'C:\/hyella\/htdocs\/feyi\/engine\/tmp\/db\/00-FF-5C-09-DA-57\/expenditure.sql' INTO TABLE expenditure","date":"1477570657","ip_address":"::1"},{"user":"35991362173","user_mail":"Hyella Nathan ( hyella@gmail.com )","user_action":"EXECUTE","table":"expenditure_payment","comment":"TRUNCATE `water_factory`.`expenditure_payment`","date":"1477570657","ip_address":"::1"},{"user":"35991362173","user_mail":"Hyella Nathan ( hyella@gmail.com )","user_action":"EXECUTE","table":"expenditure_payment","comment":"LOAD DATA INFILE 'C:\/hyella\/htdocs\/feyi\/engine\/tmp\/db\/00-FF-5C-09-DA-57\/expenditure_payment.sql' INTO TABLE expenditure_payment","date":"1477570657","ip_address":"::1"},{"user":"35991362173","user_mail":"Hyella Nathan ( hyella@gmail.com )","user_action":"EXECUTE","table":"general_settings","comment":"TRUNCATE `water_factory`.`general_settings`","date":"1477570657","ip_address":"::1"},{"user":"35991362173","user_mail":"Hyella Nathan ( hyella@gmail.com )","user_action":"EXECUTE","table":"general_settings","comment":"LOAD DATA INFILE 'C:\/hyella\/htdocs\/feyi\/engine\/tmp\/db\/00-FF-5C-09-DA-57\/general_settings.sql' INTO TABLE general_settings","date":"1477570658","ip_address":"::1"},{"user":"35991362173","user_mail":"Hyella Nathan ( hyella@gmail.com )","user_action":"EXECUTE","table":"grade_level","comment":"TRUNCATE `water_factory`.`grade_level`","date":"1477570658","ip_address":"::1"},{"user":"35991362173","user_mail":"Hyella Nathan ( hyella@gmail.com )","user_action":"EXECUTE","table":"grade_level","comment":"LOAD DATA INFILE 'C:\/hyella\/htdocs\/feyi\/engine\/tmp\/db\/00-FF-5C-09-DA-57\/grade_level.sql' INTO TABLE grade_level","date":"1477570658","ip_address":"::1"},{"user":"35991362173","user_mail":"Hyella Nathan ( hyella@gmail.com )","user_action":"EXECUTE","table":"import_items","comment":"TRUNCATE `water_factory`.`import_items`","date":"1477570658","ip_address":"::1"},{"user":"35991362173","user_mail":"Hyella Nathan ( hyella@gmail.com )","user_action":"EXECUTE","table":"import_items","comment":"LOAD DATA INFILE 'C:\/hyella\/htdocs\/feyi\/engine\/tmp\/db\/00-FF-5C-09-DA-57\/import_items.sql' INTO TABLE import_items","date":"1477570659","ip_address":"::1"},{"user":"35991362173","user_mail":"Hyella Nathan ( hyella@gmail.com )","user_action":"EXECUTE","table":"import_newsletter","comment":"TRUNCATE `water_factory`.`import_newsletter`","date":"1477570659","ip_address":"::1"},{"user":"35991362173","user_mail":"Hyella Nathan ( hyella@gmail.com )","user_action":"EXECUTE","table":"import_newsletter","comment":"LOAD DATA INFILE 'C:\/hyella\/htdocs\/feyi\/engine\/tmp\/db\/00-FF-5C-09-DA-57\/import_newsletter.sql' INTO TABLE import_newsletter","date":"1477570659","ip_address":"::1"},{"user":"35991362173","user_mail":"Hyella Nathan ( hyella@gmail.com )","user_action":"EXECUTE","table":"inventory","comment":"TRUNCATE `water_factory`.`inventory`","date":"1477570659","ip_address":"::1"},{"user":"35991362173","user_mail":"Hyella Nathan ( hyella@gmail.com )","user_action":"EXECUTE","table":"inventory","comment":"LOAD DATA INFILE 'C:\/hyella\/htdocs\/feyi\/engine\/tmp\/db\/00-FF-5C-09-DA-57\/inventory.sql' INTO TABLE inventory","date":"1477570660","ip_address":"::1"},{"user":"35991362173","user_mail":"Hyella Nathan ( hyella@gmail.com )","user_action":"EXECUTE","table":"items","comment":"TRUNCATE `water_factory`.`items`","date":"1477570660","ip_address":"::1"},{"user":"35991362173","user_mail":"Hyella Nathan ( hyella@gmail.com )","user_action":"EXECUTE","table":"items","comment":"LOAD DATA INFILE 'C:\/hyella\/htdocs\/feyi\/engine\/tmp\/db\/00-FF-5C-09-DA-57\/items.sql' INTO TABLE items","date":"1477570660","ip_address":"::1"},{"user":"35991362173","user_mail":"Hyella Nathan ( hyella@gmail.com )","user_action":"EXECUTE","table":"items_raw_data_import","comment":"TRUNCATE `water_factory`.`items_raw_data_import`","date":"1477570660","ip_address":"::1"},{"user":"35991362173","user_mail":"Hyella Nathan ( hyella@gmail.com )","user_action":"EXECUTE","table":"items_raw_data_import","comment":"LOAD DATA INFILE 'C:\/hyella\/htdocs\/feyi\/engine\/tmp\/db\/00-FF-5C-09-DA-57\/items_raw_data_import.sql' INTO TABLE items_raw_data_import","date":"1477570661","ip_address":"::1"},{"user":"35991362173","user_mail":"Hyella Nathan ( hyella@gmail.com )","user_action":"EXECUTE","table":"job_roles","comment":"TRUNCATE `water_factory`.`job_roles`","date":"1477570661","ip_address":"::1"},{"user":"35991362173","user_mail":"Hyella Nathan ( hyella@gmail.com )","user_action":"EXECUTE","table":"job_roles","comment":"LOAD DATA INFILE 'C:\/hyella\/htdocs\/feyi\/engine\/tmp\/db\/00-FF-5C-09-DA-57\/job_roles.sql' INTO TABLE job_roles","date":"1477570662","ip_address":"::1"},{"user":"35991362173","user_mail":"Hyella Nathan ( hyella@gmail.com )","user_action":"EXECUTE","table":"pay_roll_auto_generate","comment":"TRUNCATE `water_factory`.`pay_roll_auto_generate`","date":"1477570662","ip_address":"::1"},{"user":"35991362173","user_mail":"Hyella Nathan ( hyella@gmail.com )","user_action":"EXECUTE","table":"pay_roll_auto_generate","comment":"LOAD DATA INFILE 'C:\/hyella\/htdocs\/feyi\/engine\/tmp\/db\/00-FF-5C-09-DA-57\/pay_roll_auto_generate.sql' INTO TABLE pay_roll_auto_generate","date":"1477570662","ip_address":"::1"},{"user":"35991362173","user_mail":"Hyella Nathan ( hyella@gmail.com )","user_action":"EXECUTE","table":"pay_roll_post","comment":"TRUNCATE `water_factory`.`pay_roll_post`","date":"1477570662","ip_address":"::1"},{"user":"35991362173","user_mail":"Hyella Nathan ( hyella@gmail.com )","user_action":"EXECUTE","table":"pay_roll_post","comment":"LOAD DATA INFILE 'C:\/hyella\/htdocs\/feyi\/engine\/tmp\/db\/00-FF-5C-09-DA-57\/pay_roll_post.sql' INTO TABLE pay_roll_post","date":"1477570663","ip_address":"::1"},{"user":"35991362173","user_mail":"Hyella Nathan ( hyella@gmail.com )","user_action":"EXECUTE","table":"pay_row","comment":"TRUNCATE `water_factory`.`pay_row`","date":"1477570663","ip_address":"::1"},{"user":"35991362173","user_mail":"Hyella Nathan ( hyella@gmail.com )","user_action":"EXECUTE","table":"pay_row","comment":"LOAD DATA INFILE 'C:\/hyella\/htdocs\/feyi\/engine\/tmp\/db\/00-FF-5C-09-DA-57\/pay_row.sql' INTO TABLE pay_row","date":"1477570663","ip_address":"::1"},{"user":"35991362173","user_mail":"Hyella Nathan ( hyella@gmail.com )","user_action":"EXECUTE","table":"payment","comment":"TRUNCATE `water_factory`.`payment`","date":"1477570663","ip_address":"::1"},{"user":"35991362173","user_mail":"Hyella Nathan ( hyella@gmail.com )","user_action":"EXECUTE","table":"payment","comment":"LOAD DATA INFILE 'C:\/hyella\/htdocs\/feyi\/engine\/tmp\/db\/00-FF-5C-09-DA-57\/payment.sql' INTO TABLE payment","date":"1477570664","ip_address":"::1"},{"user":"35991362173","user_mail":"Hyella Nathan ( hyella@gmail.com )","user_action":"EXECUTE","table":"production","comment":"TRUNCATE `water_factory`.`production`","date":"1477570664","ip_address":"::1"},{"user":"35991362173","user_mail":"Hyella Nathan ( hyella@gmail.com )","user_action":"EXECUTE","table":"production","comment":"LOAD DATA INFILE 'C:\/hyella\/htdocs\/feyi\/engine\/tmp\/db\/00-FF-5C-09-DA-57\/production.sql' INTO TABLE production","date":"1477570664","ip_address":"::1"},{"user":"35991362173","user_mail":"Hyella Nathan ( hyella@gmail.com )","user_action":"EXECUTE","table":"production_items","comment":"TRUNCATE `water_factory`.`production_items`","date":"1477570664","ip_address":"::1"},{"user":"35991362173","user_mail":"Hyella Nathan ( hyella@gmail.com )","user_action":"EXECUTE","table":"production_items","comment":"LOAD DATA INFILE 'C:\/hyella\/htdocs\/feyi\/engine\/tmp\/db\/00-FF-5C-09-DA-57\/production_items.sql' INTO TABLE production_items","date":"1477570665","ip_address":"::1"},{"user":"35991362173","user_mail":"Hyella Nathan ( hyella@gmail.com )","user_action":"EXECUTE","table":"sales","comment":"TRUNCATE `water_factory`.`sales`","date":"1477570665","ip_address":"::1"},{"user":"35991362173","user_mail":"Hyella Nathan ( hyella@gmail.com )","user_action":"EXECUTE","table":"sales","comment":"LOAD DATA INFILE 'C:\/hyella\/htdocs\/feyi\/engine\/tmp\/db\/00-FF-5C-09-DA-57\/sales.sql' INTO TABLE sales","date":"1477570665","ip_address":"::1"},{"user":"35991362173","user_mail":"Hyella Nathan ( hyella@gmail.com )","user_action":"EXECUTE","table":"sales_items","comment":"TRUNCATE `water_factory`.`sales_items`","date":"1477570666","ip_address":"::1"},{"user":"35991362173","user_mail":"Hyella Nathan ( hyella@gmail.com )","user_action":"EXECUTE","table":"sales_items","comment":"LOAD DATA INFILE 'C:\/hyella\/htdocs\/feyi\/engine\/tmp\/db\/00-FF-5C-09-DA-57\/sales_items.sql' INTO TABLE sales_items","date":"1477570666","ip_address":"::1"},{"user":"35991362173","user_mail":"Hyella Nathan ( hyella@gmail.com )","user_action":"EXECUTE","table":"state_list","comment":"TRUNCATE `water_factory`.`state_list`","date":"1477570666","ip_address":"::1"},{"user":"35991362173","user_mail":"Hyella Nathan ( hyella@gmail.com )","user_action":"EXECUTE","table":"state_list","comment":"LOAD DATA INFILE 'C:\/hyella\/htdocs\/feyi\/engine\/tmp\/db\/00-FF-5C-09-DA-57\/state_list.sql' INTO TABLE state_list","date":"1477570667","ip_address":"::1"},{"user":"35991362173","user_mail":"Hyella Nathan ( hyella@gmail.com )","user_action":"EXECUTE","table":"stock","comment":"TRUNCATE `water_factory`.`stock`","date":"1477570670","ip_address":"::1"},{"user":"35991362173","user_mail":"Hyella Nathan ( hyella@gmail.com )","user_action":"EXECUTE","table":"stock","comment":"LOAD DATA INFILE 'C:\/hyella\/htdocs\/feyi\/engine\/tmp\/db\/00-FF-5C-09-DA-57\/stock.sql' INTO TABLE stock","date":"1477570671","ip_address":"::1"},{"user":"35991362173","user_mail":"Hyella Nathan ( hyella@gmail.com )","user_action":"EXECUTE","table":"stores","comment":"TRUNCATE `water_factory`.`stores`","date":"1477570671","ip_address":"::1"},{"user":"35991362173","user_mail":"Hyella Nathan ( hyella@gmail.com )","user_action":"EXECUTE","table":"stores","comment":"LOAD DATA INFILE 'C:\/hyella\/htdocs\/feyi\/engine\/tmp\/db\/00-FF-5C-09-DA-57\/stores.sql' INTO TABLE stores","date":"1477570672","ip_address":"::1"},{"user":"35991362173","user_mail":"Hyella Nathan ( hyella@gmail.com )","user_action":"EXECUTE","table":"transactions","comment":"TRUNCATE `water_factory`.`transactions`","date":"1477570672","ip_address":"::1"},{"user":"35991362173","user_mail":"Hyella Nathan ( hyella@gmail.com )","user_action":"EXECUTE","table":"transactions","comment":"LOAD DATA INFILE 'C:\/hyella\/htdocs\/feyi\/engine\/tmp\/db\/00-FF-5C-09-DA-57\/transactions.sql' INTO TABLE transactions","date":"1477570673","ip_address":"::1"},{"user":"35991362173","user_mail":"Hyella Nathan ( hyella@gmail.com )","user_action":"EXECUTE","table":"transactions_draft","comment":"TRUNCATE `water_factory`.`transactions_draft`","date":"1477570673","ip_address":"::1"},{"user":"35991362173","user_mail":"Hyella Nathan ( hyella@gmail.com )","user_action":"EXECUTE","table":"transactions_draft","comment":"LOAD DATA INFILE 'C:\/hyella\/htdocs\/feyi\/engine\/tmp\/db\/00-FF-5C-09-DA-57\/transactions_draft.sql' INTO TABLE transactions_draft","date":"1477570674","ip_address":"::1"},{"user":"35991362173","user_mail":"Hyella Nathan ( hyella@gmail.com )","user_action":"EXECUTE","table":"units","comment":"TRUNCATE `water_factory`.`units`","date":"1477570674","ip_address":"::1"},{"user":"35991362173","user_mail":"Hyella Nathan ( hyella@gmail.com )","user_action":"EXECUTE","table":"units","comment":"LOAD DATA INFILE 'C:\/hyella\/htdocs\/feyi\/engine\/tmp\/db\/00-FF-5C-09-DA-57\/units.sql' INTO TABLE units","date":"1477570674","ip_address":"::1"},{"user":"35991362173","user_mail":"Hyella Nathan ( hyella@gmail.com )","user_action":"EXECUTE","table":"users","comment":"TRUNCATE `water_factory`.`users`","date":"1477570674","ip_address":"::1"},{"user":"35991362173","user_mail":"Hyella Nathan ( hyella@gmail.com )","user_action":"EXECUTE","table":"users","comment":"LOAD DATA INFILE 'C:\/hyella\/htdocs\/feyi\/engine\/tmp\/db\/00-FF-5C-09-DA-57\/users.sql' INTO TABLE users","date":"1477570675","ip_address":"::1"},{"user":"35991362173","user_mail":"Hyella Nathan ( hyella@gmail.com )","user_action":"EXECUTE","table":"vendors","comment":"TRUNCATE `water_factory`.`vendors`","date":"1477570675","ip_address":"::1"},{"user":"35991362173","user_mail":"Hyella Nathan ( hyella@gmail.com )","user_action":"EXECUTE","table":"vendors","comment":"LOAD DATA INFILE 'C:\/hyella\/htdocs\/feyi\/engine\/tmp\/db\/00-FF-5C-09-DA-57\/vendors.sql' INTO TABLE vendors","date":"1477570675","ip_address":"::1"},{"user":"35991362173","user_mail":"Hyella Nathan ( hyella@gmail.com )","user_action":"EXECUTE","table":"access_roles","comment":"TRUNCATE `water_factory`.`access_roles`","date":"1477574730","ip_address":"::1"},{"user":"35991362173","user_mail":"Hyella Nathan ( hyella@gmail.com )","user_action":"EXECUTE","table":"access_roles","comment":"LOAD DATA INFILE 'C:\/hyella\/htdocs\/feyi\/engine\/tmp\/db\/00-FF-5C-09-DA-57\/access_roles.sql' INTO TABLE access_roles","date":"1477574730","ip_address":"::1"},{"user":"35991362173","user_mail":"Hyella Nathan ( hyella@gmail.com )","user_action":"EXECUTE","table":"assets","comment":"TRUNCATE `water_factory`.`assets`","date":"1477574731","ip_address":"::1"},{"user":"35991362173","user_mail":"Hyella Nathan ( hyella@gmail.com )","user_action":"EXECUTE","table":"assets","comment":"LOAD DATA INFILE 'C:\/hyella\/htdocs\/feyi\/engine\/tmp\/db\/00-FF-5C-09-DA-57\/assets.sql' INTO TABLE assets","date":"1477574731","ip_address":"::1"},{"user":"35991362173","user_mail":"Hyella Nathan ( hyella@gmail.com )","user_action":"EXECUTE","table":"assets_category","comment":"TRUNCATE `water_factory`.`assets_category`","date":"1477574731","ip_address":"::1"},{"user":"35991362173","user_mail":"Hyella Nathan ( hyella@gmail.com )","user_action":"EXECUTE","table":"assets_category","comment":"LOAD DATA INFILE 'C:\/hyella\/htdocs\/feyi\/engine\/tmp\/db\/00-FF-5C-09-DA-57\/assets_category.sql' INTO TABLE assets_category","date":"1477574731","ip_address":"::1"},{"user":"35991362173","user_mail":"Hyella Nathan ( hyella@gmail.com )","user_action":"EXECUTE","table":"branch_offices","comment":"TRUNCATE `water_factory`.`branch_offices`","date":"1477574731","ip_address":"::1"},{"user":"35991362173","user_mail":"Hyella Nathan ( hyella@gmail.com )","user_action":"EXECUTE","table":"branch_offices","comment":"LOAD DATA INFILE 'C:\/hyella\/htdocs\/feyi\/engine\/tmp\/db\/00-FF-5C-09-DA-57\/branch_offices.sql' INTO TABLE branch_offices","date":"1477574732","ip_address":"::1"},{"user":"35991362173","user_mail":"Hyella Nathan ( hyella@gmail.com )","user_action":"EXECUTE","table":"category","comment":"TRUNCATE `water_factory`.`category`","date":"1477574732","ip_address":"::1"},{"user":"35991362173","user_mail":"Hyella Nathan ( hyella@gmail.com )","user_action":"EXECUTE","table":"category","comment":"LOAD DATA INFILE 'C:\/hyella\/htdocs\/feyi\/engine\/tmp\/db\/00-FF-5C-09-DA-57\/category.sql' INTO TABLE category","date":"1477574732","ip_address":"::1"},{"user":"35991362173","user_mail":"Hyella Nathan ( hyella@gmail.com )","user_action":"EXECUTE","table":"chart_of_accounts","comment":"TRUNCATE `water_factory`.`chart_of_accounts`","date":"1477574732","ip_address":"::1"},{"user":"35991362173","user_mail":"Hyella Nathan ( hyella@gmail.com )","user_action":"EXECUTE","table":"chart_of_accounts","comment":"LOAD DATA INFILE 'C:\/hyella\/htdocs\/feyi\/engine\/tmp\/db\/00-FF-5C-09-DA-57\/chart_of_accounts.sql' INTO TABLE chart_of_accounts","date":"1477574733","ip_address":"::1"},{"user":"35991362173","user_mail":"Hyella Nathan ( hyella@gmail.com )","user_action":"EXECUTE","table":"cities_list","comment":"TRUNCATE `water_factory`.`cities_list`","date":"1477574733","ip_address":"::1"},{"user":"35991362173","user_mail":"Hyella Nathan ( hyella@gmail.com )","user_action":"EXECUTE","table":"cities_list","comment":"LOAD DATA INFILE 'C:\/hyella\/htdocs\/feyi\/engine\/tmp\/db\/00-FF-5C-09-DA-57\/cities_list.sql' INTO TABLE cities_list","date":"1477574733","ip_address":"::1"},{"user":"35991362173","user_mail":"Hyella Nathan ( hyella@gmail.com )","user_action":"EXECUTE","table":"country_list","comment":"TRUNCATE `water_factory`.`country_list`","date":"1477574734","ip_address":"::1"},{"user":"35991362173","user_mail":"Hyella Nathan ( hyella@gmail.com )","user_action":"EXECUTE","table":"country_list","comment":"LOAD DATA INFILE 'C:\/hyella\/htdocs\/feyi\/engine\/tmp\/db\/00-FF-5C-09-DA-57\/country_list.sql' INTO TABLE country_list","date":"1477574734","ip_address":"::1"},{"user":"35991362173","user_mail":"Hyella Nathan ( hyella@gmail.com )","user_action":"EXECUTE","table":"customers","comment":"TRUNCATE `water_factory`.`customers`","date":"1477574734","ip_address":"::1"},{"user":"35991362173","user_mail":"Hyella Nathan ( hyella@gmail.com )","user_action":"EXECUTE","table":"customers","comment":"LOAD DATA INFILE 'C:\/hyella\/htdocs\/feyi\/engine\/tmp\/db\/00-FF-5C-09-DA-57\/customers.sql' INTO TABLE customers","date":"1477574734","ip_address":"::1"},{"user":"35991362173","user_mail":"Hyella Nathan ( hyella@gmail.com )","user_action":"EXECUTE","table":"damages","comment":"TRUNCATE `water_factory`.`damages`","date":"1477574734","ip_address":"::1"},{"user":"35991362173","user_mail":"Hyella Nathan ( hyella@gmail.com )","user_action":"EXECUTE","table":"damages","comment":"LOAD DATA INFILE 'C:\/hyella\/htdocs\/feyi\/engine\/tmp\/db\/00-FF-5C-09-DA-57\/damages.sql' INTO TABLE damages","date":"1477574735","ip_address":"::1"},{"user":"35991362173","user_mail":"Hyella Nathan ( hyella@gmail.com )","user_action":"EXECUTE","table":"debit_and_credit","comment":"TRUNCATE `water_factory`.`debit_and_credit`","date":"1477574735","ip_address":"::1"},{"user":"35991362173","user_mail":"Hyella Nathan ( hyella@gmail.com )","user_action":"EXECUTE","table":"debit_and_credit","comment":"LOAD DATA INFILE 'C:\/hyella\/htdocs\/feyi\/engine\/tmp\/db\/00-FF-5C-09-DA-57\/debit_and_credit.sql' INTO TABLE debit_and_credit","date":"1477574735","ip_address":"::1"},{"user":"35991362173","user_mail":"Hyella Nathan ( hyella@gmail.com )","user_action":"EXECUTE","table":"debit_and_credit_draft","comment":"TRUNCATE `water_factory`.`debit_and_credit_draft`","date":"1477574735","ip_address":"::1"},{"user":"35991362173","user_mail":"Hyella Nathan ( hyella@gmail.com )","user_action":"EXECUTE","table":"debit_and_credit_draft","comment":"LOAD DATA INFILE 'C:\/hyella\/htdocs\/feyi\/engine\/tmp\/db\/00-FF-5C-09-DA-57\/debit_and_credit_draft.sql' INTO TABLE debit_and_credit_draft","date":"1477574736","ip_address":"::1"},{"user":"35991362173","user_mail":"Hyella Nathan ( hyella@gmail.com )","user_action":"EXECUTE","table":"departments","comment":"TRUNCATE `water_factory`.`departments`","date":"1477574736","ip_address":"::1"},{"user":"35991362173","user_mail":"Hyella Nathan ( hyella@gmail.com )","user_action":"EXECUTE","table":"departments","comment":"LOAD DATA INFILE 'C:\/hyella\/htdocs\/feyi\/engine\/tmp\/db\/00-FF-5C-09-DA-57\/departments.sql' INTO TABLE departments","date":"1477574736","ip_address":"::1"},{"user":"35991362173","user_mail":"Hyella Nathan ( hyella@gmail.com )","user_action":"EXECUTE","table":"discount","comment":"TRUNCATE `water_factory`.`discount`","date":"1477574736","ip_address":"::1"},{"user":"35991362173","user_mail":"Hyella Nathan ( hyella@gmail.com )","user_action":"EXECUTE","table":"discount","comment":"LOAD DATA INFILE 'C:\/hyella\/htdocs\/feyi\/engine\/tmp\/db\/00-FF-5C-09-DA-57\/discount.sql' INTO TABLE discount","date":"1477574737","ip_address":"::1"},{"user":"35991362173","user_mail":"Hyella Nathan ( hyella@gmail.com )","user_action":"EXECUTE","table":"division","comment":"TRUNCATE `water_factory`.`division`","date":"1477574737","ip_address":"::1"},{"user":"35991362173","user_mail":"Hyella Nathan ( hyella@gmail.com )","user_action":"EXECUTE","table":"division","comment":"LOAD DATA INFILE 'C:\/hyella\/htdocs\/feyi\/engine\/tmp\/db\/00-FF-5C-09-DA-57\/division.sql' INTO TABLE division","date":"1477574737","ip_address":"::1"},{"user":"35991362173","user_mail":"Hyella Nathan ( hyella@gmail.com )","user_action":"EXECUTE","table":"expenditure","comment":"TRUNCATE `water_factory`.`expenditure`","date":"1477574737","ip_address":"::1"},{"user":"35991362173","user_mail":"Hyella Nathan ( hyella@gmail.com )","user_action":"EXECUTE","table":"expenditure","comment":"LOAD DATA INFILE 'C:\/hyella\/htdocs\/feyi\/engine\/tmp\/db\/00-FF-5C-09-DA-57\/expenditure.sql' INTO TABLE expenditure","date":"1477574738","ip_address":"::1"},{"user":"35991362173","user_mail":"Hyella Nathan ( hyella@gmail.com )","user_action":"EXECUTE","table":"expenditure_payment","comment":"TRUNCATE `water_factory`.`expenditure_payment`","date":"1477574738","ip_address":"::1"},{"user":"35991362173","user_mail":"Hyella Nathan ( hyella@gmail.com )","user_action":"EXECUTE","table":"expenditure_payment","comment":"LOAD DATA INFILE 'C:\/hyella\/htdocs\/feyi\/engine\/tmp\/db\/00-FF-5C-09-DA-57\/expenditure_payment.sql' INTO TABLE expenditure_payment","date":"1477574738","ip_address":"::1"},{"user":"35991362173","user_mail":"Hyella Nathan ( hyella@gmail.com )","user_action":"EXECUTE","table":"general_settings","comment":"TRUNCATE `water_factory`.`general_settings`","date":"1477574738","ip_address":"::1"},{"user":"35991362173","user_mail":"Hyella Nathan ( hyella@gmail.com )","user_action":"EXECUTE","table":"general_settings","comment":"LOAD DATA INFILE 'C:\/hyella\/htdocs\/feyi\/engine\/tmp\/db\/00-FF-5C-09-DA-57\/general_settings.sql' INTO TABLE general_settings","date":"1477574739","ip_address":"::1"},{"user":"35991362173","user_mail":"Hyella Nathan ( hyella@gmail.com )","user_action":"EXECUTE","table":"grade_level","comment":"TRUNCATE `water_factory`.`grade_level`","date":"1477574739","ip_address":"::1"},{"user":"35991362173","user_mail":"Hyella Nathan ( hyella@gmail.com )","user_action":"EXECUTE","table":"grade_level","comment":"LOAD DATA INFILE 'C:\/hyella\/htdocs\/feyi\/engine\/tmp\/db\/00-FF-5C-09-DA-57\/grade_level.sql' INTO TABLE grade_level","date":"1477574739","ip_address":"::1"},{"user":"35991362173","user_mail":"Hyella Nathan ( hyella@gmail.com )","user_action":"EXECUTE","table":"import_items","comment":"TRUNCATE `water_factory`.`import_items`","date":"1477574739","ip_address":"::1"},{"user":"35991362173","user_mail":"Hyella Nathan ( hyella@gmail.com )","user_action":"EXECUTE","table":"import_items","comment":"LOAD DATA INFILE 'C:\/hyella\/htdocs\/feyi\/engine\/tmp\/db\/00-FF-5C-09-DA-57\/import_items.sql' INTO TABLE import_items","date":"1477574740","ip_address":"::1"},{"user":"35991362173","user_mail":"Hyella Nathan ( hyella@gmail.com )","user_action":"EXECUTE","table":"import_newsletter","comment":"TRUNCATE `water_factory`.`import_newsletter`","date":"1477574740","ip_address":"::1"},{"user":"35991362173","user_mail":"Hyella Nathan ( hyella@gmail.com )","user_action":"EXECUTE","table":"import_newsletter","comment":"LOAD DATA INFILE 'C:\/hyella\/htdocs\/feyi\/engine\/tmp\/db\/00-FF-5C-09-DA-57\/import_newsletter.sql' INTO TABLE import_newsletter","date":"1477574740","ip_address":"::1"},{"user":"35991362173","user_mail":"Hyella Nathan ( hyella@gmail.com )","user_action":"EXECUTE","table":"inventory","comment":"TRUNCATE `water_factory`.`inventory`","date":"1477574740","ip_address":"::1"},{"user":"35991362173","user_mail":"Hyella Nathan ( hyella@gmail.com )","user_action":"EXECUTE","table":"inventory","comment":"LOAD DATA INFILE 'C:\/hyella\/htdocs\/feyi\/engine\/tmp\/db\/00-FF-5C-09-DA-57\/inventory.sql' INTO TABLE inventory","date":"1477574741","ip_address":"::1"},{"user":"35991362173","user_mail":"Hyella Nathan ( hyella@gmail.com )","user_action":"EXECUTE","table":"items","comment":"TRUNCATE `water_factory`.`items`","date":"1477574741","ip_address":"::1"},{"user":"35991362173","user_mail":"Hyella Nathan ( hyella@gmail.com )","user_action":"EXECUTE","table":"items","comment":"LOAD DATA INFILE 'C:\/hyella\/htdocs\/feyi\/engine\/tmp\/db\/00-FF-5C-09-DA-57\/items.sql' INTO TABLE items","date":"1477574742","ip_address":"::1"},{"user":"35991362173","user_mail":"Hyella Nathan ( hyella@gmail.com )","user_action":"EXECUTE","table":"items_raw_data_import","comment":"TRUNCATE `water_factory`.`items_raw_data_import`","date":"1477574742","ip_address":"::1"},{"user":"35991362173","user_mail":"Hyella Nathan ( hyella@gmail.com )","user_action":"EXECUTE","table":"items_raw_data_import","comment":"LOAD DATA INFILE 'C:\/hyella\/htdocs\/feyi\/engine\/tmp\/db\/00-FF-5C-09-DA-57\/items_raw_data_import.sql' INTO TABLE items_raw_data_import","date":"1477574742","ip_address":"::1"},{"user":"35991362173","user_mail":"Hyella Nathan ( hyella@gmail.com )","user_action":"EXECUTE","table":"job_roles","comment":"TRUNCATE `water_factory`.`job_roles`","date":"1477574742","ip_address":"::1"},{"user":"35991362173","user_mail":"Hyella Nathan ( hyella@gmail.com )","user_action":"EXECUTE","table":"job_roles","comment":"LOAD DATA INFILE 'C:\/hyella\/htdocs\/feyi\/engine\/tmp\/db\/00-FF-5C-09-DA-57\/job_roles.sql' INTO TABLE job_roles","date":"1477574743","ip_address":"::1"},{"user":"35991362173","user_mail":"Hyella Nathan ( hyella@gmail.com )","user_action":"EXECUTE","table":"pay_roll_auto_generate","comment":"TRUNCATE `water_factory`.`pay_roll_auto_generate`","date":"1477574743","ip_address":"::1"},{"user":"35991362173","user_mail":"Hyella Nathan ( hyella@gmail.com )","user_action":"EXECUTE","table":"pay_roll_auto_generate","comment":"LOAD DATA INFILE 'C:\/hyella\/htdocs\/feyi\/engine\/tmp\/db\/00-FF-5C-09-DA-57\/pay_roll_auto_generate.sql' INTO TABLE pay_roll_auto_generate","date":"1477574743","ip_address":"::1"},{"user":"35991362173","user_mail":"Hyella Nathan ( hyella@gmail.com )","user_action":"EXECUTE","table":"pay_roll_post","comment":"TRUNCATE `water_factory`.`pay_roll_post`","date":"1477574743","ip_address":"::1"},{"user":"35991362173","user_mail":"Hyella Nathan ( hyella@gmail.com )","user_action":"EXECUTE","table":"pay_roll_post","comment":"LOAD DATA INFILE 'C:\/hyella\/htdocs\/feyi\/engine\/tmp\/db\/00-FF-5C-09-DA-57\/pay_roll_post.sql' INTO TABLE pay_roll_post","date":"1477574744","ip_address":"::1"},{"user":"35991362173","user_mail":"Hyella Nathan ( hyella@gmail.com )","user_action":"EXECUTE","table":"pay_row","comment":"TRUNCATE `water_factory`.`pay_row`","date":"1477574744","ip_address":"::1"},{"user":"35991362173","user_mail":"Hyella Nathan ( hyella@gmail.com )","user_action":"EXECUTE","table":"pay_row","comment":"LOAD DATA INFILE 'C:\/hyella\/htdocs\/feyi\/engine\/tmp\/db\/00-FF-5C-09-DA-57\/pay_row.sql' INTO TABLE pay_row","date":"1477574744","ip_address":"::1"},{"user":"35991362173","user_mail":"Hyella Nathan ( hyella@gmail.com )","user_action":"EXECUTE","table":"payment","comment":"TRUNCATE `water_factory`.`payment`","date":"1477574744","ip_address":"::1"},{"user":"35991362173","user_mail":"Hyella Nathan ( hyella@gmail.com )","user_action":"EXECUTE","table":"payment","comment":"LOAD DATA INFILE 'C:\/hyella\/htdocs\/feyi\/engine\/tmp\/db\/00-FF-5C-09-DA-57\/payment.sql' INTO TABLE payment","date":"1477574745","ip_address":"::1"},{"user":"35991362173","user_mail":"Hyella Nathan ( hyella@gmail.com )","user_action":"EXECUTE","table":"production","comment":"TRUNCATE `water_factory`.`production`","date":"1477574745","ip_address":"::1"},{"user":"35991362173","user_mail":"Hyella Nathan ( hyella@gmail.com )","user_action":"EXECUTE","table":"production","comment":"LOAD DATA INFILE 'C:\/hyella\/htdocs\/feyi\/engine\/tmp\/db\/00-FF-5C-09-DA-57\/production.sql' INTO TABLE production","date":"1477574745","ip_address":"::1"},{"user":"35991362173","user_mail":"Hyella Nathan ( hyella@gmail.com )","user_action":"EXECUTE","table":"production_items","comment":"TRUNCATE `water_factory`.`production_items`","date":"1477574745","ip_address":"::1"},{"user":"35991362173","user_mail":"Hyella Nathan ( hyella@gmail.com )","user_action":"EXECUTE","table":"production_items","comment":"LOAD DATA INFILE 'C:\/hyella\/htdocs\/feyi\/engine\/tmp\/db\/00-FF-5C-09-DA-57\/production_items.sql' INTO TABLE production_items","date":"1477574746","ip_address":"::1"},{"user":"35991362173","user_mail":"Hyella Nathan ( hyella@gmail.com )","user_action":"EXECUTE","table":"sales","comment":"TRUNCATE `water_factory`.`sales`","date":"1477574746","ip_address":"::1"},{"user":"35991362173","user_mail":"Hyella Nathan ( hyella@gmail.com )","user_action":"EXECUTE","table":"sales","comment":"LOAD DATA INFILE 'C:\/hyella\/htdocs\/feyi\/engine\/tmp\/db\/00-FF-5C-09-DA-57\/sales.sql' INTO TABLE sales","date":"1477574746","ip_address":"::1"},{"user":"35991362173","user_mail":"Hyella Nathan ( hyella@gmail.com )","user_action":"EXECUTE","table":"sales_items","comment":"TRUNCATE `water_factory`.`sales_items`","date":"1477574746","ip_address":"::1"},{"user":"35991362173","user_mail":"Hyella Nathan ( hyella@gmail.com )","user_action":"EXECUTE","table":"sales_items","comment":"LOAD DATA INFILE 'C:\/hyella\/htdocs\/feyi\/engine\/tmp\/db\/00-FF-5C-09-DA-57\/sales_items.sql' INTO TABLE sales_items","date":"1477574746","ip_address":"::1"},{"user":"35991362173","user_mail":"Hyella Nathan ( hyella@gmail.com )","user_action":"EXECUTE","table":"state_list","comment":"TRUNCATE `water_factory`.`state_list`","date":"1477574746","ip_address":"::1"},{"user":"35991362173","user_mail":"Hyella Nathan ( hyella@gmail.com )","user_action":"EXECUTE","table":"state_list","comment":"LOAD DATA INFILE 'C:\/hyella\/htdocs\/feyi\/engine\/tmp\/db\/00-FF-5C-09-DA-57\/state_list.sql' INTO TABLE state_list","date":"1477574747","ip_address":"::1"},{"user":"35991362173","user_mail":"Hyella Nathan ( hyella@gmail.com )","user_action":"EXECUTE","table":"stock","comment":"TRUNCATE `water_factory`.`stock`","date":"1477574749","ip_address":"::1"},{"user":"35991362173","user_mail":"Hyella Nathan ( hyella@gmail.com )","user_action":"EXECUTE","table":"stock","comment":"LOAD DATA INFILE 'C:\/hyella\/htdocs\/feyi\/engine\/tmp\/db\/00-FF-5C-09-DA-57\/stock.sql' INTO TABLE stock","date":"1477574749","ip_address":"::1"},{"user":"35991362173","user_mail":"Hyella Nathan ( hyella@gmail.com )","user_action":"EXECUTE","table":"stores","comment":"TRUNCATE `water_factory`.`stores`","date":"1477574750","ip_address":"::1"},{"user":"35991362173","user_mail":"Hyella Nathan ( hyella@gmail.com )","user_action":"EXECUTE","table":"stores","comment":"LOAD DATA INFILE 'C:\/hyella\/htdocs\/feyi\/engine\/tmp\/db\/00-FF-5C-09-DA-57\/stores.sql' INTO TABLE stores","date":"1477574750","ip_address":"::1"},{"user":"35991362173","user_mail":"Hyella Nathan ( hyella@gmail.com )","user_action":"EXECUTE","table":"transactions","comment":"TRUNCATE `water_factory`.`transactions`","date":"1477574750","ip_address":"::1"},{"user":"35991362173","user_mail":"Hyella Nathan ( hyella@gmail.com )","user_action":"EXECUTE","table":"transactions","comment":"LOAD DATA INFILE 'C:\/hyella\/htdocs\/feyi\/engine\/tmp\/db\/00-FF-5C-09-DA-57\/transactions.sql' INTO TABLE transactions","date":"1477574751","ip_address":"::1"},{"user":"35991362173","user_mail":"Hyella Nathan ( hyella@gmail.com )","user_action":"EXECUTE","table":"transactions_draft","comment":"TRUNCATE `water_factory`.`transactions_draft`","date":"1477574751","ip_address":"::1"},{"user":"35991362173","user_mail":"Hyella Nathan ( hyella@gmail.com )","user_action":"EXECUTE","table":"transactions_draft","comment":"LOAD DATA INFILE 'C:\/hyella\/htdocs\/feyi\/engine\/tmp\/db\/00-FF-5C-09-DA-57\/transactions_draft.sql' INTO TABLE transactions_draft","date":"1477574751","ip_address":"::1"},{"user":"35991362173","user_mail":"Hyella Nathan ( hyella@gmail.com )","user_action":"EXECUTE","table":"units","comment":"TRUNCATE `water_factory`.`units`","date":"1477574751","ip_address":"::1"},{"user":"35991362173","user_mail":"Hyella Nathan ( hyella@gmail.com )","user_action":"EXECUTE","table":"units","comment":"LOAD DATA INFILE 'C:\/hyella\/htdocs\/feyi\/engine\/tmp\/db\/00-FF-5C-09-DA-57\/units.sql' INTO TABLE units","date":"1477574752","ip_address":"::1"},{"user":"35991362173","user_mail":"Hyella Nathan ( hyella@gmail.com )","user_action":"EXECUTE","table":"users","comment":"TRUNCATE `water_factory`.`users`","date":"1477574752","ip_address":"::1"},{"user":"35991362173","user_mail":"Hyella Nathan ( hyella@gmail.com )","user_action":"EXECUTE","table":"users","comment":"LOAD DATA INFILE 'C:\/hyella\/htdocs\/feyi\/engine\/tmp\/db\/00-FF-5C-09-DA-57\/users.sql' INTO TABLE users","date":"1477574752","ip_address":"::1"},{"user":"35991362173","user_mail":"Hyella Nathan ( hyella@gmail.com )","user_action":"EXECUTE","table":"vendors","comment":"TRUNCATE `water_factory`.`vendors`","date":"1477574752","ip_address":"::1"},{"user":"35991362173","user_mail":"Hyella Nathan ( hyella@gmail.com )","user_action":"EXECUTE","table":"vendors","comment":"LOAD DATA INFILE 'C:\/hyella\/htdocs\/feyi\/engine\/tmp\/db\/00-FF-5C-09-DA-57\/vendors.sql' INTO TABLE vendors","date":"1477574753","ip_address":"::1"}]