{"110097197371":{"id":"110097197371","serial_num":"485","reference_id":"11009719628","1":"code","2":"desc","3":"weight","4":"cost per weight","5":"total cost","6":"markup","7":"selling","8":"color","9":"category","10":"vendor","11":"","12":"","13":"","14":"","15":"","16":"","17":"","18":"","19":"","20":"","21":"","22":"","23":"","24":"","25":"","26":"","27":"","28":"","29":"","30":"","31":"","32":"","33":"","34":"","35":"","36":"","37":"","38":"","39":"","40":""},"110097197372":{"id":"110097197372","serial_num":"486","reference_id":"11009719628","1":"67","2":"Y Full set","3":"67","4":"40","5":"2680.00","6":"100","7":"5360.00","8":"yellow","9":"full set","10":"goldy","11":"","12":"","13":"","14":"","15":"","16":"","17":"","18":"","19":"","20":"","21":"","22":"","23":"","24":"","25":"","26":"","27":"","28":"","29":"","30":"","31":"","32":"","33":"","34":"","35":"","36":"","37":"","38":"","39":"","40":""},"110097197373":{"id":"110097197373","serial_num":"487","reference_id":"11009719628","1":"126.5","2":"W\/P full set","3":"126.5","4":"40","5":"5060.00","6":"100","7":"10120.00","8":"white purple","9":"full set","10":"goldy","11":"","12":"","13":"","14":"","15":"","16":"","17":"","18":"","19":"","20":"","21":"","22":"","23":"","24":"","25":"","26":"","27":"","28":"","29":"","30":"","31":"","32":"","33":"","34":"","35":"","36":"","37":"","38":"","39":"","40":""},"110097197374":{"id":"110097197374","serial_num":"488","reference_id":"11009719628","1":"139.2","2":"Y Full Set","3":"139.2","4":"40","5":"5568.00","6":"100","7":"11136.00","8":"yellow","9":"full set","10":"goldy","11":"","12":"","13":"","14":"","15":"","16":"","17":"","18":"","19":"","20":"","21":"","22":"","23":"","24":"","25":"","26":"","27":"","28":"","29":"","30":"","31":"","32":"","33":"","34":"","35":"","36":"","37":"","38":"","39":"","40":""}}